LICENSE
MANIFEST.in
README.md
README.rst
gendocs.sh
setup.py
pygetwallpapers/__init__.py
pygetwallpapers/__init__.pyc
pygetwallpapers/pgw.py
pygetwallpapers/pgw.pyc
pygetwallpapers.egg-info/PKG-INFO
pygetwallpapers.egg-info/SOURCES.txt
pygetwallpapers.egg-info/dependency_links.txt
pygetwallpapers.egg-info/entry_points.txt
pygetwallpapers.egg-info/requires.txt
pygetwallpapers.egg-info/top_level.txt
pygetwallpapers/pgw_tools/__init__.py
pygetwallpapers/pgw_tools/__init__.pyc
pygetwallpapers/pgw_tools/constants.py
pygetwallpapers/pgw_tools/constants.pyc
pygetwallpapers/pgw_tools/functions.py
pygetwallpapers/pgw_tools/functions.pyc
pygetwallpapers/spiders/__init__.py
pygetwallpapers/spiders/__init__.pyc
pygetwallpapers/spiders/wallpaperscraft.py
pygetwallpapers/spiders/wallpaperscraft.pyc