Metadata-Version: 1.1
Name: pygetwallpapers
Version: 0.0.1
Summary: Package for download wallpapers from websites. Read help: https://github.com/yarkovaleksei/pygetwallpapers
Home-page: https://github.com/yarkovaleksei/pygetwallpapers
Author: Yarkov Aleksei
Author-email: yarkov_aleksei@mail.ru
License: MIT License
Keywords: pgw,pygetwallpapers,python get image,python load image,python get wallpapers,load wallpapers,wallpaper,get wallpapers,wallpapers download
Platform: UNKNOWN
Classifier: Environment :: Console
Classifier: Intended Audience :: Developers
Classifier: Intended Audience :: End Users/Desktop
Classifier: License :: OSI Approved :: MIT License
Classifier: Operating System :: POSIX :: Linux
Classifier: Programming Language :: Python
Classifier: Programming Language :: Python :: 2.6
Classifier: Programming Language :: Python :: 2.7
Classifier: Natural Language :: English
Classifier: Natural Language :: Russian
Classifier: Topic :: Internet :: WWW/HTTP :: Site Management :: Link Checking
